Workbook
Name Aporte: 'Ferramenta de Renda Fixa'!$D$10
Name Aporte: Ferramenta!$D$9
Name Dividendos_Mensais: 'Ferramenta de Renda Fixa'!$D$14
Name Dividendos_Mensais: Ferramenta!$D$13
Name Patrimonio: 'Ferramenta de Renda Fixa'!$D$13
Name Patrimonio: Ferramenta!$D$12
Name Rendimento_Carteira: 'Ferramenta de Renda Fixa'!$D$5
Name Rendimento_Carteira: Ferramenta!$D$5
Name Salario: 'Ferramenta de Renda Fixa'!$D$4
Name Salario: Ferramenta!$D$4
Name Sugestao_Investimento: 'Ferramenta de Renda Fixa'!$D$6
Name Sugestao_Investimento: Ferramenta!$D$6
Name Taxa_Rendimento_Anual: 'Ferramenta de Renda Fixa'!$D$12
Name Taxa_Rendimento_Anual: Ferramenta!$D$11
Name Tempo: 'Ferramenta de Renda Fixa'!$D$11
Name Tempo: Ferramenta!$D$10

Sheet Ferramenta de Renda Fixa
B3: CONFIGURAÇÕES
B4: Salário | D4: 2000
B5: Rentabilidade da Carteira | D5: 0.0125
B6: Sugestão de Investimentos (30%) | D6: =D4*30% -> 600
B7: Taxa de Juros Anual | D7: 0.15
B9: INVESTIMENTOS MENSAIS
B10: Quanto investir por mês ? | D10: 200
B11: Por Quantos Anos ? | D11: 5
B12: Taxa de Rentabilidade Mensal | D12: =D7/12 -> 0.0125
B13: Patrimônio Acumulado ? | D13: =FV(Taxa_Rendimento_Anual,Tempo*12,Aporte*-1) -> 17714.902
B14: Dividendos Mensais ? | D14: =D13*$D$5 -> 221.43627
B16: CENÁRIOS | D16: DIVIDENDOS
A17: 2 | B17: Investimento Anual em 2 anos | C17: =FV(Taxa_Rendimento_Anual,A17*12,Aporte*-1) -> 5557.6168 | D17: =C17*Rendimento_Carteira -> 69.47021
A18: 5 | B18: Investimento Anual em 5 anos | C18: =FV(Taxa_Rendimento_Anual,A18*12,Aporte*-1) -> 17714.902 | D18: =C18*Rendimento_Carteira -> 221.43627
A19: 10 | B19: Investimento Anual em 10 anos | C19: =FV(Taxa_Rendimento_Anual,A19*12,Aporte*-1) -> 55043.412 | D19: =C19*Rendimento_Carteira -> 688.04265
A20: 15 | B20: Investimento Anual em 15 anos | C20: =FV(Taxa_Rendimento_Anual,A20*12,Aporte*-1) -> 133701.35 | D20: =C20*Rendimento_Carteira -> 1671.2669
A21: 20 | B21: Investimento Anual em 20 anos | C21: =FV(Taxa_Rendimento_Anual,A21*12,Aporte*-1) -> 299447.9 | D21: =C21*Rendimento_Carteira -> 3743.0987
B23: PERFIL | D23: Agressivo
B24: Valor a ser Investido por Mês | D24: =Aporte -> 200
B26: TIPO DE RENDA FIXA | C26: PERCENTUAL | D26: VALORES
B27: CDB | C27: =VLOOKUP($D$23&"-"&B27,'Planilha de Apoio'!$B:$E,4,FALSE) -> 0.35 | D27: =C27*$D$24 -> 70
B28: LCI | C28: =VLOOKUP($D$23&"-"&B28,'Planilha de Apoio'!$B:$E,4,FALSE) -> 0.3 | D28: =C28*$D$24 -> 60
B29: LCA | C29: =VLOOKUP($D$23&"-"&B29,'Planilha de Apoio'!$B:$E,4,FALSE) -> 0.3 | D29: =C29*$D$24 -> 60
B30: SELIC | C30: =VLOOKUP($D$23&"-"&B30,'Planilha de Apoio'!$B:$E,4,FALSE) -> 0.05 | D30: =C30*$D$24 -> 10
B31: TOTAL | D31: =SUM(D27:D30) -> 200

Sheet Ferramenta
B3: CONFIGURAÇÕES
B4: Salário | D4: 726.47
B5: Rentabilidade da Carteira | D5: 1
B6: Sugestão de Investimentos (30%) | D6: =D4*30% -> 217.941
B8: INVESTIMENTOS MENSAIS
B9: Quanto investir por mês ? | D9: 337.94
B10: Por Quantos Anos ? | D10: 5
B11: Taxa de Rendimento Anual | D11: 0.01079
B12: Patrimônio Acumulado ? | D12: =FV(Taxa_Rendimento_Anual,Tempo*12,Aporte*-1) -> 28311.57
B13: Dividendos Mensais ? | D13: =D12*$D$5 -> 28311.57
B15: CENÁRIOS | D15: DIVIDENDOS
B16: Investimento Anual em 2 anos | C16: =FV(Taxa_Rendimento_Anual,$A22*12,Aporte*-1) -> 9201.3044 | D16: =C16*Rendimento_Carteira -> 9201.3044
B17: Investimento Anual em 5 anos | C17: =FV(Taxa_Rendimento_Anual,$A23*12,Aporte*-1) -> 28311.57 | D17: =C17*Rendimento_Carteira -> 28311.57
B18: Investimento Anual em 10 anos | C18: =FV(Taxa_Rendimento_Anual,$A24*12,Aporte*-1) -> 82215.467 | D18: =C18*Rendimento_Carteira -> 82215.467
B19: Investimento Anual em 15 anos | C19: =FV(Taxa_Rendimento_Anual,$A25*12,Aporte*-1) -> 184845.95 | D19: =C19*Rendimento_Carteira -> 184845.95
B20: Investimento Anual em 20 anos | C20: =FV(Taxa_Rendimento_Anual,$A26*12,Aporte*-1) -> 380249.55 | D20: =C20*Rendimento_Carteira -> 380249.55
A22: 2 | B22: PERFIL | D22: Conservador
A23: 5 | B23: Valor a ser Investido por Mês | D23: =Aporte -> 337.94
A24: 10
A25: 15 | B25: TIPO DE FII | C25: PERCENTUAL | D25: VALORES
A26: 20 | B26: PAPEL | C26: =VLOOKUP($D$22&"-"&B26,'Planilha de Apoio'!$B:$E,4,FALSE) -> 0.3 | D26: =C26*$D$23 -> 101.382
B27: TIJOLO | C27: =VLOOKUP($D$22&"-"&B27,'Planilha de Apoio'!$B:$E,4,FALSE) -> 0.5 | D27: =C27*$D$23 -> 168.97
B28: HIBRIDOS | C28: =VLOOKUP($D$22&"-"&B28,'Planilha de Apoio'!$B:$E,4,FALSE) -> 0.1 | D28: =C28*$D$23 -> 33.794
B29: FOF | C29: =VLOOKUP($D$22&"-"&B29,'Planilha de Apoio'!$B:$E,4,FALSE) -> 0.1 | D29: =C29*$D$23 -> 33.794
B30: DESENVOLVIMENTO | C30: =VLOOKUP($D$22&"-"&B30,'Planilha de Apoio'!$B:$E,4,FALSE) -> 0 | D30: =C30*$D$23 -> 0
B31: HOTELARIAS | C31: =VLOOKUP($D$22&"-"&B31,'Planilha de Apoio'!$B:$E,4,FALSE) -> 0 | D31: =C31*$D$23 -> 0
B32: TOTAL | D32: =SUM(D26:D31) -> 337.94

Sheet Planilha de Apoio
B2: CHAVE | C2: PERFIL | D2: TIPO DE FII | E2: PERCENTUAL | I2: %
B3: =$C$3&"-"&D3 -> CONSERVADOR-PAPEL | C3: CONSERVADOR | D3: PAPEL | E3: 0.3 | H3: Moderado-Tijolo | I3: =VLOOKUP(H3,$B:$E,4,FALSE) -> 0.35
B4: =$C$3&"-"&D4 -> CONSERVADOR-TIJOLO | C4: CONSERVADOR | D4: TIJOLO | E4: 0.5
B5: =$C$3&"-"&D5 -> CONSERVADOR-HIBRIDOS | C5: CONSERVADOR | D5: HIBRIDOS | E5: 0.1
B6: =$C$3&"-"&D6 -> CONSERVADOR-FOF | C6: CONSERVADOR | D6: FOF | E6: 0.1
B7: =$C$3&"-"&D7 -> CONSERVADOR-DESENVOLVIMENTO | C7: CONSERVADOR | D7: DESENVOLVIMENTO | E7: 0
B8: =$C$3&"-"&D8 -> CONSERVADOR-HOTELARIAS | C8: CONSERVADOR | D8: HOTELARIAS | E8: 0
B9: =$C$9&"-"&D9 -> MODERADO-PAPEL | C9: MODERADO | D9: PAPEL | E9: 0.32
B10: =$C$9&"-"&D10 -> MODERADO-TIJOLO | C10: MODERADO | D10: TIJOLO | E10: 0.35
B11: =$C$9&"-"&D11 -> MODERADO-HIBRIDOS | C11: MODERADO | D11: HIBRIDOS | E11: 0.08
B12: =$C$9&"-"&D12 -> MODERADO-FOF | C12: MODERADO | D12: FOF | E12: 0.05
B13: =$C$9&"-"&D13 -> MODERADO-DESENVOLVIMENTO | C13: MODERADO | D13: DESENVOLVIMENTO | E13: 0.1
B14: =$C$9&"-"&D14 -> MODERADO-HOTELARIAS | C14: MODERADO | D14: HOTELARIAS | E14: 0.1
B15: =$C$15&"-"&D15 -> AGRESSIVO-PAPEL | C15: AGRESSIVO | D15: PAPEL | E15: 0.5
B16: =$C$15&"-"&D16 -> AGRESSIVO-TIJOLO | C16: AGRESSIVO | D16: TIJOLO | E16: 0.1
B17: =$C$15&"-"&D17 -> AGRESSIVO-HIBRIDOS | C17: AGRESSIVO | D17: HIBRIDOS | E17: 0.05
B18: =$C$15&"-"&D18 -> AGRESSIVO-FOF | C18: AGRESSIVO | D18: FOF | E18: 0.05
B19: =$C$15&"-"&D19 -> AGRESSIVO-DESENVOLVIMENTO | C19: AGRESSIVO | D19: DESENVOLVIMENTO | E19: 0.2
B20: =$C$15&"-"&D20 -> AGRESSIVO-HOTELARIAS | C20: AGRESSIVO | D20: HOTELARIAS | E20: 0.1
B22: CHAVE | C22: PERFIL | D22: TIPO DE FII | E22: PERCENTUAL | I22: %
B23: =$C$3&"-"&D23 -> CONSERVADOR-CDB | C23: CONSERVADOR | D23: CDB | E23: 0.4 | H23: AGRESSIVO-SELIC | I23: =VLOOKUP(H23,B:E,4,FALSE) -> 0.05
B24: =$C$3&"-"&D24 -> CONSERVADOR-LCI | C24: CONSERVADOR | D24: LCI | E24: 0.1
B25: =$C$3&"-"&D25 -> CONSERVADOR-LCA | C25: CONSERVADOR | D25: LCA | E25: 0.1
B26: =$C$3&"-"&D26 -> CONSERVADOR-SELIC | C26: CONSERVADOR | D26: SELIC | E26: 0.4
B27: =$C$9&"-"&D27 -> MODERADO-CDB | C27: MODERADO | D27: CDB | E27: 0.4
B28: =$C$9&"-"&D28 -> MODERADO-LCI | C28: MODERADO | D28: LCI | E28: 0.2
B29: =$C$9&"-"&D29 -> MODERADO-LCA | C29: MODERADO | D29: LCA | E29: 0.2
B30: =$C$9&"-"&D30 -> MODERADO-SELIC | C30: MODERADO | D30: SELIC | E30: 0.2
B31: =$C$15&"-"&D31 -> AGRESSIVO-CDB | C31: AGRESSIVO | D31: CDB | E31: 0.35
B32: =$C$15&"-"&D32 -> AGRESSIVO-LCI | C32: AGRESSIVO | D32: LCI | E32: 0.3
B33: =$C$15&"-"&D33 -> AGRESSIVO-LCA | C33: AGRESSIVO | D33: LCA | E33: 0.3
B34: =$C$15&"-"&D34 -> AGRESSIVO-SELIC | C34: AGRESSIVO | D34: SELIC | E34: 0.05
